Flask_JWTAuthorization-0.0.5.dist-info/DESCRIPTION.rst
Flask_JWTAuthorization-0.0.5.dist-info/LICENSE.txt
Flask_JWTAuthorization-0.0.5.dist-info/METADATA
Flask_JWTAuthorization-0.0.5.dist-info/RECORD
Flask_JWTAuthorization-0.0.5.dist-info/WHEEL
Flask_JWTAuthorization-0.0.5.dist-info/metadata.json
Flask_JWTAuthorization-0.0.5.dist-info/top_level.txt
flask_jwtauthorization/__init__.py
