Metadata-Version: 2.0
Name: Flask-JWTAuthorization
Version: 0.0.5
Summary: Authorization framework based on JWT for Flask applications
Home-page: https://github.com/sergiofcasado/flask-jwtauthorization
Author: Sergio Fernandez Casado
Author-email: sfernand@cern.ch
License: GPLv3
Keywords: flask jwt json web token authorization
Platform: UNKNOWN
Classifier: Development Status :: 3 - Alpha
Classifier: Intended Audience :: Developers
Classifier: Environment :: Web Environment
Classifier: Topic :: Internet :: WWW/HTTP :: Dynamic Content
Classifier: Topic :: Software Development :: Libraries :: Python Modules
Classifier: Operating System :: OS Independent
Classifier: License :: OSI Approved :: GNU General Public License v3 (GPLv3)
Classifier: Programming Language :: Python :: 2
Classifier: Programming Language :: Python :: 2.7
Classifier: Programming Language :: Python :: 3
Classifier: Programming Language :: Python :: 3.3
Classifier: Programming Language :: Python :: 3.4
Classifier: Programming Language :: Python :: 3.5
Classifier: Programming Language :: Python :: 3.6
Requires-Dist: Flask (>=0.12)
Requires-Dist: PyJWT (>=1.4.0)
